qmtbt/__init__.py
qmtbt/qmtbroker.py
qmtbt/qmtfeed.py
qmtbt/qmtstore.py
qmtbt-0.2.5.dist-info/LICENSE
qmtbt-0.2.5.dist-info/METADATA
qmtbt-0.2.5.dist-info/WHEEL
qmtbt-0.2.5.dist-info/RECORD
