Metadata-Version: 2.3
Name: qmtbt
Version: 0.2.5
Summary: 
Author: pluto
Author-email: mayuanchi1029@gmail.com
Requires-Python: >=3.9,<3.13
Classifier: Programming Language :: Python :: 3
Classifier: Programming Language :: Python :: 3.9
Classifier: Programming Language :: Python :: 3.10
Classifier: Programming Language :: Python :: 3.11
Classifier: Programming Language :: Python :: 3.12
Requires-Dist: backtrader (>=1.9.78.123,<2.0.0.0)
Requires-Dist: matplotlib (>=3.9.0,<4.0.0)
Requires-Dist: schedule (>=1.2.0,<2.0.0)
Requires-Dist: xtquant (>=240613.1.1,<240614.0.0)
